MANIFEST.in
README.txt
setup.cfg
setup.py
collective/__init__.py
collective.googledocsviewer.egg-info/PKG-INFO
collective.googledocsviewer.egg-info/SOURCES.txt
collective.googledocsviewer.egg-info/dependency_links.txt
collective.googledocsviewer.egg-info/entry_points.txt
collective.googledocsviewer.egg-info/namespace_packages.txt
collective.googledocsviewer.egg-info/not-zip-safe
collective.googledocsviewer.egg-info/paster_plugins.txt
collective.googledocsviewer.egg-info/requires.txt
collective.googledocsviewer.egg-info/top_level.txt
collective/googledocsviewer/__init__.py
collective/googledocsviewer/configure.zcml
collective/googledocsviewer/googledocsviewer.pt
collective/googledocsviewer/interfaces.py
collective/googledocsviewer/views.py
collective/googledocsviewer/profiles/default/browserlayer.xml
collective/googledocsviewer/profiles/default/metadata.xml
collective/googledocsviewer/profiles/default/registry.xml
collective/googledocsviewer/profiles/default/types/File.xml
docs/HISTORY.txt
docs/INSTALL.txt
docs/LICENSE.txt