Metadata-Version: 1.0
Name: collective.googledocsviewer
Version: 1.0b1
Summary: Use google docs viewer to display embed version of your office files
Home-page: http://svn.plone.org/svn/collective/
Author: JeanMichel FRANCOIS aka toutpt
Author-email: toutpt@gmail.com
License: GPL
Platform: UNKNOWN
Classifier: Framework :: Plone
Classifier: Programming Language :: Python
